pedalboard_native.cpython-313-x86_64-linux-gnu.so
pedalboard/AudioUnitParser.h
pedalboard/AudioUnitParser.mm
pedalboard/BufferUtils.h
pedalboard/ExternalPlugin.h
pedalboard/JuceHeader.h
pedalboard/JucePlugin.h
pedalboard/Plugin.h
pedalboard/PluginContainer.h
pedalboard/RubberbandPlugin.h
pedalboard/StreamUtils.h
pedalboard/TimeStretch.h
pedalboard/__init__.py
pedalboard/_pedalboard.py
pedalboard/midi_utils.py
pedalboard/process.h
pedalboard/py.typed
pedalboard/python_bindings.cpp
pedalboard/version.py
pedalboard/io/AudioFile.h
pedalboard/io/AudioFileInit.h
pedalboard/io/AudioStream.h
pedalboard/io/LameMP3AudioFormat.h
pedalboard/io/PythonFileLike.h
pedalboard/io/PythonInputStream.h
pedalboard/io/PythonOutputStream.h
pedalboard/io/ReadableAudioFile.h
pedalboard/io/ResampledReadableAudioFile.h
pedalboard/io/StreamResampler.h
pedalboard/io/WriteableAudioFile.h
pedalboard/io/__init__.py
pedalboard/juce_overrides/include_juce_audio_basics.cpp
pedalboard/juce_overrides/include_juce_audio_basics.mm
pedalboard/juce_overrides/include_juce_audio_devices.cpp
pedalboard/juce_overrides/include_juce_audio_devices.mm
pedalboard/juce_overrides/include_juce_audio_formats.cpp
pedalboard/juce_overrides/include_juce_audio_formats.mm
pedalboard/juce_overrides/include_juce_audio_processors.cpp
pedalboard/juce_overrides/include_juce_audio_processors.mm
pedalboard/juce_overrides/include_juce_core.cpp
pedalboard/juce_overrides/include_juce_core.mm
pedalboard/juce_overrides/include_juce_data_structures.cpp
pedalboard/juce_overrides/include_juce_data_structures.mm
pedalboard/juce_overrides/include_juce_dsp.cpp
pedalboard/juce_overrides/include_juce_dsp.mm
pedalboard/juce_overrides/include_juce_events.cpp
pedalboard/juce_overrides/include_juce_events.mm
pedalboard/juce_overrides/include_juce_graphics.cpp
pedalboard/juce_overrides/include_juce_graphics.mm
pedalboard/juce_overrides/include_juce_gui_basics.cpp
pedalboard-0.9.21.dist-info/METADATA
pedalboard-0.9.21.dist-info/WHEEL
pedalboard-0.9.21.dist-info/RECORD
pedalboard-0.9.21.dist-info/licenses/LICENSE
pedalboard-0.9.21.dist-info/licenses/NOTICE
pedalboard-0.9.21.dist-info/sboms/auditwheel.cdx.json
