Metadata-Version: 2.2
Name: pedalboard
Version: 0.9.21
Summary: A Python library for adding effects to audio.
Author-Email: Peter Sobot <psobot@spotify.com>
License:                     GNU GENERAL PUBLIC LICENSE
Classifier: Development Status :: 4 - Beta
Classifier: License :: OSI Approved :: GNU General Public License v3 (GPLv3)
Classifier: Operating System :: MacOS
Classifier: Operating System :: Microsoft :: Windows
Classifier: Operating System :: POSIX :: Linux
Classifier: Programming Language :: C++
Classifier: Programming Language :: Python
Classifier: Topic :: Multimedia :: Sound/Audio
Classifier: Programming Language :: Python :: 3.10
Classifier: Programming Language :: Python :: 3.11
Classifier: Programming Language :: Python :: 3.12
Classifier: Programming Language :: Python :: 3.13
Classifier: Programming Language :: Python :: 3.14
Requires-Python: >=3.10
Requires-Dist: numpy
Provides-Extra: test
Requires-Dist: pytest; extra == "test"
Requires-Dist: pyright; extra == "test"
Requires-Dist: mutagen; extra == "test"
Requires-Dist: pytest-cov; extra == "test"
Requires-Dist: pytest-mock; extra == "test"
Requires-Dist: tqdm; extra == "test"
Requires-Dist: psutil; extra == "test"
Requires-Dist: mypy; extra == "test"
Requires-Dist: pyright; extra == "test"
Requires-Dist: mido; extra == "test"
